README.md
setup.py
datatool/__init__.py
datatool/chunkdb.py
datatool/lcs.py
datatool/mapreduce.py
datatool/roc.py
datatool/singleton.py
datatool/string.py
datatool/time.py
datatool/utils.py
datatool/version.py
datatool/cuda/__init__.py
datatool/cuda/base.py
datatool/cuda/cluster.py
datatool_python.egg-info/PKG-INFO
datatool_python.egg-info/SOURCES.txt
datatool_python.egg-info/dependency_links.txt
datatool_python.egg-info/not-zip-safe
datatool_python.egg-info/requires.txt
datatool_python.egg-info/top_level.txt
tests/test_cuda.py
tests/test_lcs.py
tests/test_mapreduce.py
tests/test_singleton.py
tests/test_string.py
tests/test_time.py
tests/test_utils.py