Metadata-Version: 2.1
Name: datatool-python
Version: 1.3.4
Summary: A datatool library.
Home-page: UNKNOWN
Author: Alexander Khlebushchev
License: MIT
Platform: UNKNOWN
